react_ipywidgets/__init__.py
react_ipywidgets/core.py
reacton/__init__.py
reacton/_version.py
reacton/bqplot.py
reacton/core.py
reacton/core_test.py
reacton/find.py
reacton/find_test.py
reacton/generate.py
reacton/generate_test.py
reacton/ipycanvas.py
reacton/ipyvue.py
reacton/ipyvuetify.py
reacton/ipywidgets.py
reacton/logging.py
reacton/patch.py
reacton/patch_display.py
reacton/py.typed
reacton/rx.py
reacton/test.vue
reacton/test_rx.py
reacton/utils.py
reacton/utils_test.py
reacton/work.py
reacton/deprecated/__init__.py
reacton/deprecated/ipyvuetify.py
reacton-1.8.1.dist-info/METADATA
reacton-1.8.1.dist-info/WHEEL
reacton-1.8.1.dist-info/licenses/LICENSE
reacton-1.8.1.dist-info/RECORD
