Metadata-Version: 2.1
Name: reacton
Version: 1.8.1
Project-URL: Home, https://www.github.com/widgetti/reacton
Project-URL: Documentation, https://reacton.solara.dev
Project-URL: Source code, https://www.github.com/widgetti/reacton
Author-email: "Maarten A. Breddels" <maartenbreddels@gmail.com>
License: The MIT License (MIT)
License-File: LICENSE
Classifier: Environment :: Web Environment
Classifier: Framework :: Jupyter
Classifier: License :: OSI Approved :: MIT License
Classifier: Programming Language :: Python :: 3.6
Classifier: Programming Language :: Python :: 3.7
Classifier: Programming Language :: Python :: 3.8
Classifier: Programming Language :: Python :: 3.9
Classifier: Programming Language :: Python :: 3.10
Classifier: Programming Language :: Python :: 3.11
Classifier: Topic :: Software Development :: User Interfaces
Requires-Dist: ipywidgets
Requires-Dist: typing-extensions>=4.1.1
Provides-Extra: dev
Requires-Dist: black; extra == 'dev'
Requires-Dist: bqplot; extra == 'dev'
Requires-Dist: bump2version; extra == 'dev'
Requires-Dist: coverage; extra == 'dev'
Requires-Dist: flake8; extra == 'dev'
Requires-Dist: ipykernel; extra == 'dev'
Requires-Dist: ipyvuetify; extra == 'dev'
Requires-Dist: jinja2; extra == 'dev'
Requires-Dist: mypy; extra == 'dev'
Requires-Dist: numpy; extra == 'dev'
Requires-Dist: pandas; extra == 'dev'
Requires-Dist: pre-commit; extra == 'dev'
Requires-Dist: pytest; extra == 'dev'
Requires-Dist: pytest-cov; extra == 'dev'
Provides-Extra: generate
Requires-Dist: black; extra == 'generate'
Requires-Dist: bqplot; extra == 'generate'
Requires-Dist: jinja2; extra == 'generate'
Requires-Dist: mypy; extra == 'generate'
